local_server/__init__.py
local_server/server.py
local_server-0.1.1.dist-info/METADATA
local_server-0.1.1.dist-info/WHEEL
local_server-0.1.1.dist-info/entry_points.txt
local_server-0.1.1.dist-info/top_level.txt
local_server-0.1.1.dist-info/RECORD
